ezgatr/__init__.py
ezgatr/interfaces/__init__.py
ezgatr/interfaces/plane.py
ezgatr/interfaces/point.py
ezgatr/interfaces/pseudoscalar.py
ezgatr/interfaces/reflection.py
ezgatr/interfaces/rotation.py
ezgatr/interfaces/scalar.py
ezgatr/interfaces/translation.py
ezgatr/nets/README.md
ezgatr/nets/__init__.py
ezgatr/nets/mv_only_gatr.py
ezgatr/nn/__init__.py
ezgatr/nn/functional/__init__.py
ezgatr/nn/functional/activation.py
ezgatr/nn/functional/attention.py
ezgatr/nn/functional/basis/geometric_product.pt
ezgatr/nn/functional/basis/outer_product.pt
ezgatr/nn/functional/dual.py
ezgatr/nn/functional/linear.py
ezgatr/nn/functional/norm.py
ezgatr/nn/modules/__init__.py
ezgatr/nn/modules/linear.py
ezgatr/nn/modules/norm.py
ezgatr/utils/__init__.py
ezgatr/utils/debug.py
ezgatr/utils/logger.py
ezgatr-0.1.0a0.dist-info/LICENSE
ezgatr-0.1.0a0.dist-info/METADATA
ezgatr-0.1.0a0.dist-info/WHEEL
ezgatr-0.1.0a0.dist-info/RECORD
