Metadata-Version: 2.1
Name: ezgatr
Version: 0.1.0a0
Summary: 
Author: guest400123064
Author-email: wangy49@alumni.upenn.edu
Requires-Python: >=3.9,<4.0
Classifier: Programming Language :: Python :: 3
Classifier: Programming Language :: Python :: 3.9
Classifier: Programming Language :: Python :: 3.10
Classifier: Programming Language :: Python :: 3.11
Classifier: Programming Language :: Python :: 3.12
Requires-Dist: einops (>=0.8.0,<0.9.0)
Requires-Dist: numpy (<2.1)
Requires-Dist: torch (>=2.4.1,<3.0.0)
